run_para/__init__.py
run_para/functions.py
run_para/run-para
run_para/run_para.py
run_para/segment.py
run_para/symbols.py
run_para/tui.py
run_para/version.py
run_para-1.2.20.dist-info/licenses/LICENSE
run_para-1.2.20.dist-info/METADATA
run_para-1.2.20.dist-info/WHEEL
run_para-1.2.20.dist-info/entry_points.txt
run_para-1.2.20.dist-info/top_level.txt
run_para-1.2.20.dist-info/RECORD
