Metadata-Version: 2.4
Name: run-para
Version: 1.2.20
Summary: Interactive Parallel SSH jobs manager
Home-page: https://github.com/joknarf/run-para
Author: Franck Jouvanceau
Maintainer: Franck Jouvanceau
License: MIT License
Project-URL: Homepage, https://joknarf.github.io/joknarf-tools/
Project-URL: Documentation, https://github.com/joknarf/run-para/blob/main/README.md
Project-URL: Repository, https://github.com/joknarf/run-para.git
Keywords: run,command,cli,parallel,jobs
Classifier: Development Status :: 5 - Production/Stable
Classifier: Intended Audience :: System Administrators
Classifier: License :: OSI Approved :: MIT License
Classifier: Operating System :: POSIX
Classifier: Operating System :: Unix
Classifier: Operating System :: Microsoft :: Windows
Classifier: Operating System :: MacOS
Classifier: Programming Language :: Python
Classifier: Programming Language :: Python :: 3
Classifier: Programming Language :: Python :: 3.6
Classifier: Programming Language :: Python :: 3.7
Classifier: Programming Language :: Python :: 3.8
Classifier: Programming Language :: Python :: 3.9
Classifier: Programming Language :: Python :: 3.10
Classifier: Programming Language :: Python :: 3.11
Classifier: Topic :: Software Development :: Libraries :: Python Modules
Classifier: Topic :: System :: Clustering
Classifier: Topic :: System :: Networking
Classifier: Topic :: System :: Systems Administration
Requires-Python: >=3.6
License-File: LICENSE
Requires-Dist: colorama
Requires-Dist: dataclasses>=0.6; python_version < "3.7"
Requires-Dist: argcomplete>=3.0.4
Requires-Dist: windows-curses>=2.3.3; platform_system == "Windows"
Dynamic: license-file
